gpucv.cpython-37m-x86_64-linux-gnu.so
gpucv-0.0.4.3.dist-info/DESCRIPTION.rst
gpucv-0.0.4.3.dist-info/METADATA
gpucv-0.0.4.3.dist-info/RECORD
gpucv-0.0.4.3.dist-info/WHEEL
gpucv-0.0.4.3.dist-info/dependency_links.txt
gpucv-0.0.4.3.dist-info/metadata.json
gpucv-0.0.4.3.dist-info/top_level.txt
