Metadata-Version: 2.0
Name: gpucv
Version: 0.0.4.3
Summary: Run image processing algos on your GPU
Home-page: http://example.com/
Author: Shrikumaran PB
Author-email: pbshrikumaran@gmail.com
License: UNKNOWN
Platform: UNKNOWN
